Counters/Synchronous Ring Counter/D_ff.v
// module D_ff(d, clk, q, q_bar);
module D_ff(d, clk, q, rst, set);
    input d, clk, rst, set;
    output q;
    reg q;

    always @(posedge clk) begin
        if (rst) begin
            if (set) begin
                q <= 1;
            end 
            else begin
                q <=0;
            end
        end else begin
        q <= d;          
        end
    end
endmodule

FSM/FSM_Seq.v
module FSM_Seq(clk, rst, inp, out);
    input clk, rst, inp;
    output out;
    wire q1, q2, q3;
    D_ff d1((q2&&q3)||(q1&&~q3), clk, q1, rst, 1'b0);
    D_ff d2((q2&&~q3)||(~q1&&~q2&&q3), clk, q2, rst, 1'b0);
    D_ff d3((~q3&&inp)||(q2&&~q3)||(q1&&~q3), clk, q3, rst, 1'b0);
    D_ff d4(q1||(~q2&&~q3&&inp) , clk, out, rst, 1'b0);
endmodule

FSM/tb_seq.v
module tb_seq();
    reg clk, rst, inp;
    wire out;
    FSM_Seq DUT(.clk(clk), .rst(rst), .inp(inp), .out(out));
    always #2 clk = ~clk;
    initial begin
        clk = 1'b0;
        rst = 0;
        inp = 0;
        #5 rst = 1'b1;
        #20 rst = 1'b0;
        #10 inp = 1;
        #60 inp = 0;
    end
    initial begin
        $dumpfile("FSM_Seq.vcd");
        $dumpvars(0, tb_seq);
        $monitor("SimTime=%g, Clk=%b, Reset=%b, Input=%b -> Output=%b", $time, clk, rst, inp, out);
        #150 $finish;
    end
endmodule

FSM/FSM_Seq.vcd
$date
	Tue May 18 13:50:51 2021
$end
$version
	Icarus Verilog
$end
$timescale
	1s
$end
$scope module tb_seq $end
$var wire 1 ! out $end
$var reg 1 " clk $end
$var reg 1 # inp $end
$var reg 1 $ rst $end
$scope module DUT $end
$var wire 1 " clk $end
$var wire 1 # inp $end
$var wire 1 $ rst $end
$var wire 1 % q3 $end
$var wire 1 & q2 $end
$var wire 1 ' q1 $end
$var wire 1 ! out $end
$scope module d1 $end
$var wire 1 " clk $end
$var wire 1 ( d $end
$var wire 1 $ rst $end
$var wire 1 ) set $end
$var reg 1 ' q $end
$upscope $end
$scope module d2 $end
$var wire 1 " clk $end
$var wire 1 * d $end
$var wire 1 $ rst $end
$var wire 1 + set $end
$var reg 1 & q $end
$upscope $end
$scope module d3 $end
$var wire 1 " clk $end
$var wire 1 , d $end
$var wire 1 $ rst $end
$var wire 1 - set $end
$var reg 1 % q $end
$upscope $end
$scope module d4 $end
$var wire 1 " clk $end
$var wire 1 . d $end
$var wire 1 $ rst $end
$var wire 1 / set $end
$var reg 1 ! q $end
$upscope $end
$upscope $end
$upscope $end
$enddefinitions $end
#0
$dumpvars
0/
x.
0-
x,
0+
x*
0)
x(
x'
x&
x%
0$
0#
0"
x!
$end
#2
1"
#4
0"
#5
1$
#6
0,
0*
0(
0.
0!
0%
0&
0'
1"
#8
0"
#10
1"
#12
0"
#14
1"
#16
0"
#18
1"
#20
0"
#22
1"
#24
0"
#25
0$
#26
1"
#28
0"
#30
1"
#32
0"
#34
1"
#35
1,
1.
1#
#36
0"
#38
0.
0,
1*
1!
1%
1"
#40
0"
#42
1,
1&
0%
0!
1"
#44
0"
#46
0,
0*
1(
1%
1"
#48
0"
#50
1,
1.
1'
0&
0%
1"
#52
0"
#54
0,
0(
1!
1%
1"
#56
0"
#58
1,
1.
0'
0%
1"
#60
0"
#62
0.
0,
1*
1%
1"
#64
0"
#66
1,
1&
0%
0!
1"
#68
0"
#70
0,
0*
1(
1%
1"
#72
0"
#74
1,
1.
1'
0&
0%
1"
#76
0"
#78
0,
0(
1!
1%
1"
#80
0"
#82
1,
1.
0'
0%
1"
#84
0"
#86
0.
0,
1*
1%
1"
#88
0"
#90
1,
1&
0%
0!
1"
#92
0"
#94
0,
0*
1(
1%
1"
#95
0#
#96
0"
#98
1,
1.
1'
0&
0%
1"
#100
0"
#102
0,
0(
1!
1%
1"
#104
0"
#106
0.
0'
0%
1"
#108
0"
#110
0!
1"
