Counters/Synchronous 4-bit Gray-Code Counter/SR_new.v
module SR_new(S, R, clk, Q, rst);
    input S, R, clk, rst;
    output reg Q;

    always @(posedge clk) begin
        if (rst) begin
          Q <= 0;
        end
        else if(S == 1) begin
            Q <= 1;
            // Qbar <= 0;
        end
        else if(R == 1) begin
            Q <= 0;
            // Qbar <= 1;
        end
        else if(S == 0 & R == 0) begin
            Q <= Q;
            // Qbar = Qbar;
        end
    end
endmodule

Counters/Synchronous 4-bit Gray-Code Counter/GCC.v
module GCC(clk, q1, q2, q3, q4, rst);
    input clk, rst;
    output q1, q2, q3, q4;
    wire s1,r1,s2,r2,s3,r3,s4,r4;

    assign s1 = q2 && q3 && q4;
    assign s2 = ~q1 && q3 && ~q4;
    assign s3 = (~q1 && q4) || (~q2 && q4);
    assign s4 = ~q3 && (~q1 || q2);
    
    assign r1 = ~q2 && ~q3 && ~q4;
    assign r2 = q1 && ~q3 && q4;
    assign r3 = (q1 && ~q4) || (q2 && ~q4);
    assign r4 = q3 && (q1 || ~q2);

    SR_new S1(s1, r1, clk, q1, rst);
    SR_new S2(s2, r2, clk, q2, rst);
    SR_new S3(s3, r3, clk, q3, rst);
    SR_new S4(s4, r4, clk, q4, rst);

endmodule

Counters/Synchronous 4-bit Gray-Code Counter/tb_GCC.v
module tb_GCC;
    wire q1, q2, q3, q4;
    reg clk, rst;

    GCC DUT(.clk(clk), .q1(q1), .q2(q2), .q3(q3), .q4(q4), .rst(rst));

    always #2 clk = ~clk;
    initial begin
        clk = 1'b0;
        rst = 0;
        #5 rst = 1'b1;
        #20 rst = 1'b0;
    end
    
    initial begin
        $dumpfile("GCC.vcd");
        $dumpvars(0, tb_GCC);
        $monitor("SimTime=%g, Clk=%b, Reset=%b Output: %b %b %b %b", $time, clk, rst, q1, q2, q3, q4);
        #90 $finish;
    end
endmodule

Counters/Synchronous 4-bit Gray-Code Counter/GCC.vcd
$date
	Tue May 18 13:26:04 2021
$end
$version
	Icarus Verilog
$end
$timescale
	1s
$end
$scope module tb_GCC $end
$var wire 1 ! q4 $end
$var wire 1 " q3 $end
$var wire 1 # q2 $end
$var wire 1 $ q1 $end
$var reg 1 % clk $end
$var reg 1 & rst $end
$scope module DUT $end
$var wire 1 % clk $end
$var wire 1 ' r1 $end
$var wire 1 ( r2 $end
$var wire 1 ) r3 $end
$var wire 1 * r4 $end
$var wire 1 & rst $end
$var wire 1 + s1 $end
$var wire 1 , s2 $end
$var wire 1 - s3 $end
$var wire 1 . s4 $end
$var wire 1 ! q4 $end
$var wire 1 " q3 $end
$var wire 1 # q2 $end
$var wire 1 $ q1 $end
$scope module S1 $end
$var wire 1 ' R $end
$var wire 1 + S $end
$var wire 1 % clk $end
$var wire 1 & rst $end
$var reg 1 $ Q $end
$upscope $end
$scope module S2 $end
$var wire 1 ( R $end
$var wire 1 , S $end
$var wire 1 % clk $end
$var wire 1 & rst $end
$var reg 1 # Q $end
$upscope $end
$scope module S3 $end
$var wire 1 ) R $end
$var wire 1 - S $end
$var wire 1 % clk $end
$var wire 1 & rst $end
$var reg 1 " Q $end
$upscope $end
$scope module S4 $end
$var wire 1 * R $end
$var wire 1 . S $end
$var wire 1 % clk $end
$var wire 1 & rst $end
$var reg 1 ! Q $end
$upscope $end
$upscope $end
$upscope $end
$enddefinitions $end
#0
$dumpvars
x.
x-
x,
x+
x*
x)
x(
x'
0&
0%
x$
x#
x"
x!
$end
#2
1%
#4
0%
#5
1&
#6
1'
0-
0,
1.
0)
0(
0+
0*
0!
0"
0#
0$
1%
#8
0%
#10
1%
#12
0%
#14
1%
#16
0%
#18
1%
#20
0%
#22
1%
#24
0%
#25
0&
#26
0'
1-
1!
1%
#28
0%
#30
0.
1*
1"
1%
#32
0%
#34
0-
1,
0!
1%
#36
0%
#38
0*
1)
1#
1%
#40
0%
#42
1.
0,
0"
1%
#44
0%
#46
0)
1-
1!
1%
#48
0%
#50
0.
1+
1"
1%
#52
0%
#54
0-
1*
1$
1%
#56
0%
#58
1)
0+
0!
1%
#60
0%
#62
1.
0*
0"
1%
#64
0%
#66
0)
1(
1!
1%
#68
0%
#70
1-
0.
0#
1%
#72
0%
#74
0(
1*
1"
1%
#76
0%
#78
1)
0-
0!
1%
#80
0%
#82
1'
0*
0"
1%
#84
0%
#86
1.
0)
0$
1%
#88
0%
#90
0'
1-
1!
1%
